gocept.testdb-6.0-py3.11-nspkg.pth
gocept/testdb/README.rst
gocept/testdb/__init__.py
gocept/testdb/base.py
gocept/testdb/cmdline.py
gocept/testdb/mysql.py
gocept/testdb/postgres.py
gocept/testdb/testing.py
gocept/testdb/tests/__init__.py
gocept/testdb/tests/test_cmdline.py
gocept/testdb/tests/test_mysql.py
gocept/testdb/tests/test_postgres.py
gocept.testdb-6.0.dist-info/LICENSE.txt
gocept.testdb-6.0.dist-info/METADATA
gocept.testdb-6.0.dist-info/WHEEL
gocept.testdb-6.0.dist-info/entry_points.txt
gocept.testdb-6.0.dist-info/namespace_packages.txt
gocept.testdb-6.0.dist-info/top_level.txt
gocept.testdb-6.0.dist-info/RECORD
