Metadata-Version: 2.1
Name: gocept.testdb
Version: 6.0
Summary: Creates and drops temporary databases for testing purposes.
Home-page: https://github.com/gocept/gocept.testdb
Author: gocept <mail at gocept dot com>
Author-email: mail@gocept.com
License: ZPL 2.1
Classifier: Development Status :: 5 - Production/Stable
Classifier: Intended Audience :: Developers
Classifier: License :: OSI Approved
Classifier: License :: OSI Approved :: Zope Public License
Classifier: Natural Language :: English
Classifier: Operating System :: OS Independent
Classifier: Programming Language :: Python
Classifier: Programming Language :: Python :: 3
Classifier: Programming Language :: Python :: 3.7
Classifier: Programming Language :: Python :: 3.8
Classifier: Programming Language :: Python :: 3.9
Classifier: Programming Language :: Python :: 3.10
Classifier: Programming Language :: Python :: 3.11
Classifier: Programming Language :: Python :: Implementation :: CPython
Classifier: Topic :: Database
Classifier: Topic :: Software Development :: Testing
Classifier: Topic :: Utilities
Requires-Python: >=3.7
License-File: LICENSE.txt
Requires-Dist: setuptools
Requires-Dist: SQLAlchemy (<3,>=1.2)
Provides-Extra: test
Requires-Dist: gocept.testing ; extra == 'test'
Requires-Dist: mock ; extra == 'test'
Requires-Dist: psycopg2 ; extra == 'test'
Requires-Dist: PyMySQL ; extra == 'test'
